PythonOpencvShiyongjiaocheng/README.md
PythonOpencvShiyongjiaocheng/__init__.py
PythonOpencvShiyongjiaocheng/__main__.py
PythonOpencvShiyongjiaocheng/file.epub
PythonOpencvShiyongjiaocheng/index.html
PythonOpencvShiyongjiaocheng/css/__init__.py
PythonOpencvShiyongjiaocheng/css/annotations.css
PythonOpencvShiyongjiaocheng/css/main.css
PythonOpencvShiyongjiaocheng/css/normalize.css
PythonOpencvShiyongjiaocheng/css/popup.css
PythonOpencvShiyongjiaocheng/font/__init__.py
PythonOpencvShiyongjiaocheng/font/fontello.eot
PythonOpencvShiyongjiaocheng/font/fontello.svg
PythonOpencvShiyongjiaocheng/font/fontello.ttf
PythonOpencvShiyongjiaocheng/font/fontello.woff
PythonOpencvShiyongjiaocheng/img/__init__.py
PythonOpencvShiyongjiaocheng/img/annotator-glyph-sprite.png
PythonOpencvShiyongjiaocheng/img/annotator-icon-sprite.png
PythonOpencvShiyongjiaocheng/img/apple-touch-icon.png
PythonOpencvShiyongjiaocheng/img/cancelfullscreen.png
PythonOpencvShiyongjiaocheng/img/close.png
PythonOpencvShiyongjiaocheng/img/fullscreen.png
PythonOpencvShiyongjiaocheng/img/loader.gif
PythonOpencvShiyongjiaocheng/img/menu-icon.png
PythonOpencvShiyongjiaocheng/img/save.png
PythonOpencvShiyongjiaocheng/img/saved.png
PythonOpencvShiyongjiaocheng/img/settings-s.png
PythonOpencvShiyongjiaocheng/img/settings.png
PythonOpencvShiyongjiaocheng/img/star.png
PythonOpencvShiyongjiaocheng/js/__init__.py
PythonOpencvShiyongjiaocheng/js/epub.js
PythonOpencvShiyongjiaocheng/js/epub.min.js
PythonOpencvShiyongjiaocheng/js/epub.min.map
PythonOpencvShiyongjiaocheng/js/hooks.min.js
PythonOpencvShiyongjiaocheng/js/hooks.min.map
PythonOpencvShiyongjiaocheng/js/reader.js
PythonOpencvShiyongjiaocheng/js/reader.js.map
PythonOpencvShiyongjiaocheng/js/reader.min.js
PythonOpencvShiyongjiaocheng/js/reader.min.map
PythonOpencvShiyongjiaocheng/js/hooks/__init__.py
PythonOpencvShiyongjiaocheng/js/hooks/extensions/__init__.py
PythonOpencvShiyongjiaocheng/js/hooks/extensions/highlight.js
python_opencv_shiyongjiaocheng-2024.3.5.0.dist-info/METADATA
python_opencv_shiyongjiaocheng-2024.3.5.0.dist-info/WHEEL
python_opencv_shiyongjiaocheng-2024.3.5.0.dist-info/entry_points.txt
python_opencv_shiyongjiaocheng-2024.3.5.0.dist-info/top_level.txt
python_opencv_shiyongjiaocheng-2024.3.5.0.dist-info/RECORD
